polevault/__init__.py
polevault/config.py
polevault/encryption.py
polevault-0.1.4.dist-info/LICENSE
polevault-0.1.4.dist-info/METADATA
polevault-0.1.4.dist-info/WHEEL
polevault-0.1.4.dist-info/entry_points.txt
polevault-0.1.4.dist-info/top_level.txt
polevault-0.1.4.dist-info/RECORD
