Metadata-Version: 2.1
Name: polevault
Version: 0.1.4
Summary: Encrypts and decrypts credentials
Home-page: https://paulopes.github.io/polevault/
Author: Paulo Lopes
Author-email: palopes@cisco.com
License: UNKNOWN
Platform: UNKNOWN
Requires-Dist: click
